interactions/ext/help/__init__.py
interactions/ext/help/help.py
interactions_help-0.0.5.dist-info/LICENSE
interactions_help-0.0.5.dist-info/METADATA
interactions_help-0.0.5.dist-info/WHEEL
interactions_help-0.0.5.dist-info/top_level.txt
interactions_help-0.0.5.dist-info/RECORD
