Metadata-Version: 2.1
Name: interactions-help
Version: 0.0.5
Summary: An extension library for interactions.py to create help command.
Home-page: https://github.com/ItsRqtl/interactions-help
Author: ItsRqtl
Author-email: itsrqtl@gmail.com
License: MIT
Classifier: Programming Language :: Python :: 3
Classifier: Development Status :: 4 - Beta
Classifier: License :: OSI Approved :: MIT License
Classifier: Operating System :: OS Independent
Requires-Python: >=3.8.6
License-File: LICENSE
Requires-Dist: dinteractions-paginator (>=2.0.2)
Requires-Dist: discord-py-interactions (>=4.3.1)
